qinfo.cpython-310-x86_64-linux-gnu.so
qinfo_python-0.1.4.dist-info/METADATA
qinfo_python-0.1.4.dist-info/WHEEL
qinfo_python-0.1.4.dist-info/top_level.txt
qinfo_python-0.1.4.dist-info/RECORD
