Metadata-Version: 2.1
Name: qinfo-python
Version: 0.1.4
Summary: Python3 bindings for qinfo
Home-page: https://github.com/el-wumbus/qinfo-python
Author: Decator
Author-email: decator.c@proton.me
License: LGPLv3
Platform: UNKNOWN
Classifier: Operating System :: Unix
